gw_phenom-1.0.1.data/scripts/phenom-chirp-time
gw_phenom-1.0.1.data/scripts/phenom-ringdown-frequency
phenom/__init__.py
phenom/match/__init__.py
phenom/match/match.py
phenom/pn/__init__.py
phenom/pn/pn.py
phenom/psd/__init__.py
phenom/psd/psd.py
phenom/testing/__init__.py
phenom/testing/prec_angle_helper.py
phenom/utils/__init__.py
phenom/utils/formats.py
phenom/utils/remnant.py
phenom/utils/swsh.py
phenom/utils/utils.py
phenom/utils/QNMdata/QNMphenomd.py
phenom/utils/QNMdata/__init__.py
phenom/waveform/__init__.py
phenom/waveform/phenomD.py
phenom/waveform/phenomP.py
phenom/waveform/waveform.py
gw_phenom-1.0.1.dist-info/LICENSE
gw_phenom-1.0.1.dist-info/METADATA
gw_phenom-1.0.1.dist-info/WHEEL
gw_phenom-1.0.1.dist-info/top_level.txt
gw_phenom-1.0.1.dist-info/RECORD
