Metadata-Version: 2.1
Name: gw-phenom
Version: 1.0.1
Summary: Phenomenological Waveform Models
Home-page: https://github.com/Cyberface/phenom
Author: Sebastian Khan
Author-email: KhanS22@Cardiff.ac.uk
License: UNKNOWN
Download-URL: https://github.com/Cyberface/phenom/archive/master.zip
Platform: UNKNOWN
